xzero_file/README.md
xzero_file/__init__.py
xzero_file/app.py
xzero_file/requirements.txt
xzero_file/service.py
xzero_file/assets/index.css
xzero_file/assets/index.html
xzero_file/assets/index.js
xzero_file/assets/images/dir.svg
xzero_file/assets/images/file.svg
xzero_file-0.0.8.dist-info/METADATA
xzero_file-0.0.8.dist-info/WHEEL
xzero_file-0.0.8.dist-info/top_level.txt
xzero_file-0.0.8.dist-info/RECORD
